loopstructuralviusualisation/__init__.py
loopstructuralviusualisation-0.1.0.dist-info/METADATA
loopstructuralviusualisation-0.1.0.dist-info/WHEEL
loopstructuralviusualisation-0.1.0.dist-info/top_level.txt
loopstructuralviusualisation-0.1.0.dist-info/RECORD
